multitest/MultiTest.py
multitest/__init__.py
multiple_hypothesis_testing-0.2.1.dist-info/LICENSE
multiple_hypothesis_testing-0.2.1.dist-info/METADATA
multiple_hypothesis_testing-0.2.1.dist-info/WHEEL
multiple_hypothesis_testing-0.2.1.dist-info/top_level.txt
multiple_hypothesis_testing-0.2.1.dist-info/RECORD
