Metadata-Version: 2.1
Name: multiple-hypothesis-testing
Version: 0.2.1
Summary: Several methods of combining P-values
Home-page: https://github.com/alonkipnis/higher-criticism-test
Download-URL: https://github.com/alonkipnis/higher-criticism-test
Author: Alon Kipnis
Author-email: alonkipnis@gmail.com
Classifier: Programming Language :: Python :: 3
Classifier: License :: OSI Approved :: MIT License
Classifier: Operating System :: OS Independent
Requires-Python: >=3.6
License-File: LICENSE
Requires-Dist: numpy>=1.6
Requires-Dist: matplotlib>=3.6
